<?xml version="1.0" encoding="UTF-8" ?>
<!DOCTYPE mapper
        PUBLIC "-//mybatis.org//DTD Mapper 3.0//EN"
        "http://mybatis.org/dtd/mybatis-3-mapper.dtd">
<mapper namespace="bo.ucb.edu.ingsoft.dao.CategoryDao">
    <select id="findByCategoryId" resultType="bo.ucb.edu.ingsoft.model.Category">
        SELECT
               category_id as categoryId,
               name as name,
               photo_id as photoId,
               path as path,
               status as status,
               tx_id as txId,
               tx_host as txHost,
               tx_user as txUserId,
               tx_date as txDate,
               tx_update as txUpdate
        FROM category
        WHERE
            category_id = #{categoryId} and status=1
    </select>

    <insert id="categoryinsert" parameterType="bo.ucb.edu.ingsoft.model.Category">
        INSERT INTO category (`category_id`, `name`, `status`, `tx_id`, `tx_host`, `tx_user`, `tx_date`, `tx_update`, `photo_id`, `path`) VALUES (
            null, #{name}, 1, #{transaction.txId}, #{transaction.txHost},
            #{transaction.txUserId}, #{transaction.txDate}, #{transaction.txUpdate}, #{photoId}, #{path}
        )
    </insert>

    <update id="categoryupdate" parameterType="bo.ucb.edu.ingsoft.model.Category">
        UPDATE category
        SET name = #{name}
        WHERE category_id = #{categoryId} and status=1

    </update>

    <update id="categorydelete" parameterType="bo.ucb.edu.ingsoft.model.Category">
        UPDATE category
        SET status = 0
        WHERE category_id = #{categoryId} and status=1
    </update>

    <select id="categories" resultType="bo.ucb.edu.ingsoft.dto.CategoryRequest">
        SELECT
            a.category_id as categoryId,
            a.name as nameCategory,
            b.photo_id as photoId,
            a.path as path
        FROM category a, photo b
        where a.status=1
        and a.photo_id=b.photo_id

    </select>

    <insert id="createphotoCategory" parameterType="bo.ucb.edu.ingsoft.model.Photos">
        INSERT INTO photo
        VALUES (
            null,#{categoryId},#{photoPath},1,#{transaction.txId}, "127.0.0.1",
            #{transaction.txUserId}, #{transaction.txDate}, #{transaction.txUpdate})
    </insert>

    <select id="findImageByCategoryId" resultType="bo.ucb.edu.ingsoft.model.Photos">
        SELECT
            category_id as categoryId,
            photo_path as photoPath
        FROM photo
        where status=1
        and category_id=#{categoryId}

    </select>


</mapper>
